sylt/top.py
sylt/common/__init__.py
sylt/common/utils.py
sylt/runtime/__init__.py
sylt/runtime/commands.py
sylt/sdk/__init__.py
sylt/sdk/client.py
sylt-0.0.36.dist-info/METADATA
sylt-0.0.36.dist-info/WHEEL
sylt-0.0.36.dist-info/top_level.txt
sylt-0.0.36.dist-info/RECORD
